mousetumorpy/__init__.py
mousetumorpy/_version.py
mousetumorpy/cli.py
mousetumorpy/configuration.py
mousetumorpy/lungs.py
mousetumorpy/nnunet.py
mousetumorpy/register.py
mousetumorpy/track.py
mousetumorpy-0.0.4.dist-info/licenses/LICENSE
mousetumorpy-0.0.4.dist-info/METADATA
mousetumorpy-0.0.4.dist-info/WHEEL
mousetumorpy-0.0.4.dist-info/entry_points.txt
mousetumorpy-0.0.4.dist-info/top_level.txt
mousetumorpy-0.0.4.dist-info/RECORD
