Metadata-Version: 2.4
Name: mousetumorpy
Version: 0.0.4
Author-email: EPFL Center for Imaging <imaging@epfl.ch>
License:                     GNU AFFERO GENERAL PUBLIC LICENSE
Project-URL: homepage, https://github.com/mousetumorpy/mousetumorpy
Project-URL: repository, https://github.com/mousetumorpy/mousetumorpy
Classifier: Development Status :: 2 - Pre-Alpha
Classifier: Intended Audience :: Developers
Classifier: License :: OSI Approved :: BSD License
Classifier: Operating System :: OS Independent
Classifier: Programming Language :: Python
Classifier: Programming Language :: Python :: 3
Classifier: Programming Language :: Python :: 3 :: Only
Classifier: Programming Language :: Python :: 3.9
Classifier: Programming Language :: Python :: 3.10
Classifier: Programming Language :: Python :: 3.11
Classifier: Programming Language :: Python :: 3.12
Classifier: Topic :: Scientific/Engineering :: Image Processing
Requires-Python: >=3.9
License-File: LICENSE
Requires-Dist: PyYAML
Requires-Dist: appdirs
Requires-Dist: blosc2
Requires-Dist: nnunetv2
Requires-Dist: pooch
Requires-Dist: numpy
Requires-Dist: pandas
Requires-Dist: scikit-image
Requires-Dist: ultralytics
Requires-Dist: trackpy
Requires-Dist: laptrack
Requires-Dist: vedo
Dynamic: license-file
